pdf_slicer/__init__.py
pdf_slicer/gui.py
pdf_slicer/py.typed
pdf_slicer/splitter.py
pdf_slicer-2023.1.0.dist-info/METADATA
pdf_slicer-2023.1.0.dist-info/WHEEL
pdf_slicer-2023.1.0.dist-info/licenses/LICENSE
pdf_slicer-2023.1.0.dist-info/RECORD
